maskouk/__init__.py
maskouk/collocation_const.py
maskouk/collocationdictionary.py
maskouk/collocations.py
maskouk/data/collocations.sqlite
maskouk/data/semantic.sqlite
maskouk_pysqlite-0.1.dist-info/METADATA
maskouk_pysqlite-0.1.dist-info/RECORD
maskouk_pysqlite-0.1.dist-info/WHEEL
maskouk_pysqlite-0.1.dist-info/top_level.txt
