Metadata-Version: 2.1
Name: maskouk-pysqlite
Version: 0.1
Summary: maskouk: Arabic Dictionary for Collocations - python + sqlite
Home-page: http://maskouk.sourceforge.net/
Author: Taha Zerrouki
Author-email: taha.zerrouki@gmail.com
License: GPL
Platform: UNKNOWN
Classifier: Development Status :: 5 - Production/Stable
Classifier: Intended Audience :: End Users/Desktop
Classifier: Operating System :: OS Independent
Classifier: Programming Language :: Python
Requires-Dist: pyarabic (>=0.6.2)
